jinja2_outputfile/__init__.py
jinja2_outputfile/_pathlib.py
jinja2_outputfile-0.5.1.dist-info/licenses/LICENSE
jinja2_outputfile-0.5.1.dist-info/METADATA
jinja2_outputfile-0.5.1.dist-info/WHEEL
jinja2_outputfile-0.5.1.dist-info/top_level.txt
jinja2_outputfile-0.5.1.dist-info/zip-safe
jinja2_outputfile-0.5.1.dist-info/RECORD
