Metadata-Version: 2.4
Name: jinja2-outputfile
Version: 0.5.1
Summary: Jinja2 extension that redirects output to output file(s)
Home-page: https://github.com/jenisys/jinja2-outputfile
Download-URL: https://pypi.org/project/jinja2-outputfile
Author: Jens Engel
Author-email: Jens Engel <jenisys@noreply.github.com>
License-Expression: BSD-3-Clause
Project-URL: Homepage, https://github.com/jenisys/jinja2-outputfile
Project-URL: Repository, https://github.com/jenisys/jinja2-outputfile
Project-URL: Download, https://pypi.org/project/jinja2-outputfile
Project-URL: Issues, https://github.com/jenisys/jinja2-outputfile/issues/
Keywords: Jinja2,jinja2,template-extension
Platform: any
Classifier: Development Status :: 5 - Production/Stable
Classifier: Environment :: Console
Classifier: Intended Audience :: Developers
Classifier: Operating System :: OS Independent
Classifier: Programming Language :: Python :: 2.7
Classifier: Programming Language :: Python :: 3.5
Classifier: Programming Language :: Python :: 3.6
Classifier: Programming Language :: Python :: 3.7
Classifier: Programming Language :: Python :: 3.8
Classifier: Programming Language :: Python :: 3.9
Classifier: Programming Language :: Python :: 3.10
Classifier: Programming Language :: Python :: 3.11
Classifier: Programming Language :: Python :: 3.12
Classifier: Programming Language :: Python :: 3.13
Classifier: Topic :: Software Development :: Code Generators
Requires-Python: !=3.0.*,!=3.1.*,!=3.2.*,!=3.3.*,!=3.4.*,>=2.7
License-File: LICENSE
Requires-Dist: jinja2>=3.0; python_version >= "3.6"
Requires-Dist: jinja2<3.0; python_version < "3.6"
Requires-Dist: pathlib2; python_version <= "3.4"
Dynamic: download-url
Dynamic: license-file
